flake8_typing_only_imports/__init__.py
flake8_typing_only_imports/checker.py
flake8_typing_only_imports/constants.py
flake8_typing_only_imports/plugin.py
flake8_typing_only_imports/py.typed
flake8_typing_only_imports/types.py
flake8_typing_only_imports-0.2.2.dist-info/entry_points.txt
flake8_typing_only_imports-0.2.2.dist-info/LICENSE
flake8_typing_only_imports-0.2.2.dist-info/WHEEL
flake8_typing_only_imports-0.2.2.dist-info/METADATA
flake8_typing_only_imports-0.2.2.dist-info/RECORD
