Metadata-Version: 2.1
Name: flake8-typing-only-imports
Version: 0.2.2
Summary: A flake8 plugin to flag imports exclusively used for type annotations
Home-page: https://github.com/sondrelg/flake8-typing-only-imports
License: BSD-2-Clause
Keywords: flake8,linting,type hint,typing,imports
Author: Sondre Lillebø Gundersen
Author-email: sondrelg@live.no
Requires-Python: >=3.7,<4.0
Classifier: Development Status :: 2 - Pre-Alpha
Classifier: Environment :: Console
Classifier: Intended Audience :: Developers
Classifier: License :: OSI Approved :: BSD License
Classifier: Operating System :: OS Independent
Classifier: Programming Language :: Python
Classifier: Programming Language :: Python :: 3
Classifier: Programming Language :: Python :: 3.10
Classifier: Programming Language :: Python :: 3.7
Classifier: Programming Language :: Python :: 3.8
Classifier: Programming Language :: Python :: 3.9
Classifier: Topic :: Software Development :: Quality Assurance
Classifier: Typing :: Typed
Requires-Dist: flake8
Project-URL: Documentation, https://github.com/sondrelg/flake8-typing-only-imports
Project-URL: Repository, https://github.com/sondrelg/flake8-typing-only-imports
